splashbuilder-0.0.data/scripts/cel2wst
splashbuilder-0.0.data/scripts/map2wsm
splashbuilder-0.0.data/scripts/splashbuilder
ws_splashbuilder/__init__.py
ws_splashbuilder/__main__.py
ws_splashbuilder/_version.py
ws_splashbuilder/cel2wst.py
ws_splashbuilder/map2wsm.py
ws_splashbuilder/splashbuilder.py
splashbuilder-0.0.dist-info/LICENSE
splashbuilder-0.0.dist-info/METADATA
splashbuilder-0.0.dist-info/WHEEL
splashbuilder-0.0.dist-info/top_level.txt
splashbuilder-0.0.dist-info/RECORD
