Metadata-Version: 2.1
Name: splashbuilder
Version: 0.0
Summary: A tool to build WonderSwan Color boot splash
Home-page: https://github.com/godzil/splashbuilder
Author: Manoel <godzil> Trapier
Author-email: wssplashbuilder@godzil.net
License: UNKNOWN
Platform: UNKNOWN
Classifier: Programming Language :: Python :: 3
Classifier: Operating System :: OS Independent
Classifier: Development Status :: 2 - Pre-Alpha
Classifier: Environment :: Console
Classifier: License :: OSI Approved :: BSD License
Requires-Python: >=3.6
